{
  "info": {
    "_postman_id": "b9d5f636-9ac3-4ad9-8f12-5a6e4bbf2e01",
    "name": "MaDemo Platform API",
    "description": "Collection complete pour la plateforme de tracking de jeu: profils, matchmaking, economie, ugc, moderation, leaderboard, monitoring.",
    "schema": "https://schema.getpostman.com/json/collection/v2.1.0/collection.json"
  },
  "item": [
    {
      "name": "Monitoring",
      "item": [
        {
          "name": "Health",
          "request": {
            "method": "GET",
            "header": [],
            "url": {
              "raw": "{{baseUrl}}/actuator/health",
              "host": [
                "{{baseUrl}}"
              ],
              "path": [
                "actuator",
                "health"
              ]
            }
          }
        },
        {
          "name": "Prometheus Metrics",
          "request": {
            "method": "GET",
            "header": [],
            "url": {
              "raw": "{{baseUrl}}/actuator/prometheus",
              "host": [
                "{{baseUrl}}"
              ],
              "path": [
                "actuator",
                "prometheus"
              ]
            }
          }
        }
      ]
    },
    {
      "name": "Profils",
      "item": [
        {
          "name": "Create Profil",
          "request": {
            "auth": {
              "type": "basic",
              "basic": [
                {
                  "key": "username",
                  "value": "{{username}}",
                  "type": "string"
                },
                {
                  "key": "password",
                  "value": "{{password}}",
                  "type": "string"
                }
              ]
            },
            "method": "POST",
            "header": [
              {
                "key": "Content-Type",
                "value": "application/json"
              }
            ],
            "body": {
              "mode": "raw",
              "raw": "{\n  \"name\": \"PlayerOne\",\n  \"email\": \"player1@example.com\"\n}"
            },
            "url": {
              "raw": "{{baseUrl}}/api/profils",
              "host": [
                "{{baseUrl}}"
              ],
              "path": [
                "api",
                "profils"
              ]
            }
          }
        },
        {
          "name": "List Profils",
          "request": {
            "auth": {
              "type": "basic",
              "basic": [
                {
                  "key": "username",
                  "value": "{{username}}",
                  "type": "string"
                },
                {
                  "key": "password",
                  "value": "{{password}}",
                  "type": "string"
                }
              ]
            },
            "method": "GET",
            "header": [],
            "url": {
              "raw": "{{baseUrl}}/api/profils",
              "host": [
                "{{baseUrl}}"
              ],
              "path": [
                "api",
                "profils"
              ]
            }
          }
        },
        {
          "name": "Get Profil By Id",
          "request": {
            "auth": {
              "type": "basic",
              "basic": [
                {
                  "key": "username",
                  "value": "{{username}}",
                  "type": "string"
                },
                {
                  "key": "password",
                  "value": "{{password}}",
                  "type": "string"
                }
              ]
            },
            "method": "GET",
            "header": [],
            "url": {
              "raw": "{{baseUrl}}/api/profils/1",
              "host": [
                "{{baseUrl}}"
              ],
              "path": [
                "api",
                "profils",
                "1"
              ]
            }
          }
        }
      ]
    },
    {
      "name": "Matchmaking",
      "item": [
        {
          "name": "Create Match",
          "request": {
            "auth": {
              "type": "basic",
              "basic": [
                {
                  "key": "username",
                  "value": "{{username}}",
                  "type": "string"
                },
                {
                  "key": "password",
                  "value": "{{password}}",
                  "type": "string"
                }
              ]
            },
            "method": "POST",
            "header": [
              {
                "key": "Content-Type",
                "value": "application/json"
              }
            ],
            "body": {
              "mode": "raw",
              "raw": "{\n  \"playerOneId\": 1,\n  \"playerTwoId\": 2\n}"
            },
            "url": {
              "raw": "{{baseUrl}}/api/matches",
              "host": [
                "{{baseUrl}}"
              ],
              "path": [
                "api",
                "matches"
              ]
            }
          }
        },
        {
          "name": "Complete Match",
          "request": {
            "auth": {
              "type": "basic",
              "basic": [
                {
                  "key": "username",
                  "value": "{{username}}",
                  "type": "string"
                },
                {
                  "key": "password",
                  "value": "{{password}}",
                  "type": "string"
                }
              ]
            },
            "method": "POST",
            "header": [
              {
                "key": "Content-Type",
                "value": "application/json"
              }
            ],
            "body": {
              "mode": "raw",
              "raw": "{\n  \"winnerId\": 1\n}"
            },
            "url": {
              "raw": "{{baseUrl}}/api/matches/1/complete",
              "host": [
                "{{baseUrl}}"
              ],
              "path": [
                "api",
                "matches",
                "1",
                "complete"
              ]
            }
          }
        },
        {
          "name": "List Matches",
          "request": {
            "auth": {
              "type": "basic",
              "basic": [
                {
                  "key": "username",
                  "value": "{{username}}",
                  "type": "string"
                },
                {
                  "key": "password",
                  "value": "{{password}}",
                  "type": "string"
                }
              ]
            },
            "method": "GET",
            "header": [],
            "url": {
              "raw": "{{baseUrl}}/api/matches",
              "host": [
                "{{baseUrl}}"
              ],
              "path": [
                "api",
                "matches"
              ]
            }
          }
        }
      ]
    },
    {
      "name": "Economy",
      "item": [
        {
          "name": "Credit Wallet",
          "request": {
            "auth": {
              "type": "basic",
              "basic": [
                {
                  "key": "username",
                  "value": "{{username}}",
                  "type": "string"
                },
                {
                  "key": "password",
                  "value": "{{password}}",
                  "type": "string"
                }
              ]
            },
            "method": "POST",
            "header": [
              {
                "key": "Content-Type",
                "value": "application/json"
              }
            ],
            "body": {
              "mode": "raw",
              "raw": "{\n  \"profilId\": 1,\n  \"type\": \"CREDIT\",\n  \"amount\": 250.00,\n  \"reason\": \"Daily reward\"\n}"
            },
            "url": {
              "raw": "{{baseUrl}}/api/economy/transactions",
              "host": [
                "{{baseUrl}}"
              ],
              "path": [
                "api",
                "economy",
                "transactions"
              ]
            }
          }
        },
        {
          "name": "Debit Wallet",
          "request": {
            "auth": {
              "type": "basic",
              "basic": [
                {
                  "key": "username",
                  "value": "{{username}}",
                  "type": "string"
                },
                {
                  "key": "password",
                  "value": "{{password}}",
                  "type": "string"
                }
              ]
            },
            "method": "POST",
            "header": [
              {
                "key": "Content-Type",
                "value": "application/json"
              }
            ],
            "body": {
              "mode": "raw",
              "raw": "{\n  \"profilId\": 1,\n  \"type\": \"DEBIT\",\n  \"amount\": 50.00,\n  \"reason\": \"Shop purchase\"\n}"
            },
            "url": {
              "raw": "{{baseUrl}}/api/economy/transactions",
              "host": [
                "{{baseUrl}}"
              ],
              "path": [
                "api",
                "economy",
                "transactions"
              ]
            }
          }
        },
        {
          "name": "Wallet History",
          "request": {
            "auth": {
              "type": "basic",
              "basic": [
                {
                  "key": "username",
                  "value": "{{username}}",
                  "type": "string"
                },
                {
                  "key": "password",
                  "value": "{{password}}",
                  "type": "string"
                }
              ]
            },
            "method": "GET",
            "header": [],
            "url": {
              "raw": "{{baseUrl}}/api/economy/wallet/1/transactions",
              "host": [
                "{{baseUrl}}"
              ],
              "path": [
                "api",
                "economy",
                "wallet",
                "1",
                "transactions"
              ]
            }
          }
        }
      ]
    },
    {
      "name": "UGC",
      "item": [
        {
          "name": "Create Content",
          "request": {
            "auth": {
              "type": "basic",
              "basic": [
                {
                  "key": "username",
                  "value": "{{username}}",
                  "type": "string"
                },
                {
                  "key": "password",
                  "value": "{{password}}",
                  "type": "string"
                }
              ]
            },
            "method": "POST",
            "header": [
              {
                "key": "Content-Type",
                "value": "application/json"
              }
            ],
            "body": {
              "mode": "raw",
              "raw": "{\n  \"authorProfilId\": 1,\n  \"title\": \"Guide build sniper\",\n  \"body\": \"Mon build recommande pour la saison.\"\n}"
            },
            "url": {
              "raw": "{{baseUrl}}/api/ugc",
              "host": [
                "{{baseUrl}}"
              ],
              "path": [
                "api",
                "ugc"
              ]
            }
          }
        },
        {
          "name": "List Content",
          "request": {
            "auth": {
              "type": "basic",
              "basic": [
                {
                  "key": "username",
                  "value": "{{username}}",
                  "type": "string"
                },
                {
                  "key": "password",
                  "value": "{{password}}",
                  "type": "string"
                }
              ]
            },
            "method": "GET",
            "header": [],
            "url": {
              "raw": "{{baseUrl}}/api/ugc",
              "host": [
                "{{baseUrl}}"
              ],
              "path": [
                "api",
                "ugc"
              ]
            }
          }
        },
        {
          "name": "Publish Content",
          "request": {
            "auth": {
              "type": "basic",
              "basic": [
                {
                  "key": "username",
                  "value": "{{username}}",
                  "type": "string"
                },
                {
                  "key": "password",
                  "value": "{{password}}",
                  "type": "string"
                }
              ]
            },
            "method": "POST",
            "header": [],
            "url": {
              "raw": "{{baseUrl}}/api/ugc/1/publish",
              "host": [
                "{{baseUrl}}"
              ],
              "path": [
                "api",
                "ugc",
                "1",
                "publish"
              ]
            }
          }
        }
      ]
    },
    {
      "name": "Moderation",
      "item": [
        {
          "name": "Create Report",
          "request": {
            "auth": {
              "type": "basic",
              "basic": [
                {
                  "key": "username",
                  "value": "{{username}}",
                  "type": "string"
                },
                {
                  "key": "password",
                  "value": "{{password}}",
                  "type": "string"
                }
              ]
            },
            "method": "POST",
            "header": [
              {
                "key": "Content-Type",
                "value": "application/json"
              }
            ],
            "body": {
              "mode": "raw",
              "raw": "{\n  \"contentId\": 1,\n  \"reporterProfilId\": 2,\n  \"reason\": \"Contenu toxique\"\n}"
            },
            "url": {
              "raw": "{{baseUrl}}/api/moderation/reports",
              "host": [
                "{{baseUrl}}"
              ],
              "path": [
                "api",
                "moderation",
                "reports"
              ]
            }
          }
        },
        {
          "name": "List Reports",
          "request": {
            "auth": {
              "type": "basic",
              "basic": [
                {
                  "key": "username",
                  "value": "{{username}}",
                  "type": "string"
                },
                {
                  "key": "password",
                  "value": "{{password}}",
                  "type": "string"
                }
              ]
            },
            "method": "GET",
            "header": [],
            "url": {
              "raw": "{{baseUrl}}/api/moderation/reports",
              "host": [
                "{{baseUrl}}"
              ],
              "path": [
                "api",
                "moderation",
                "reports"
              ]
            }
          }
        },
        {
          "name": "Resolve Report (Admin)",
          "request": {
            "auth": {
              "type": "basic",
              "basic": [
                {
                  "key": "username",
                  "value": "{{adminUsername}}",
                  "type": "string"
                },
                {
                  "key": "password",
                  "value": "{{adminPassword}}",
                  "type": "string"
                }
              ]
            },
            "method": "POST",
            "header": [],
            "url": {
              "raw": "{{baseUrl}}/api/moderation/reports/1/resolve",
              "host": [
                "{{baseUrl}}"
              ],
              "path": [
                "api",
                "moderation",
                "reports",
                "1",
                "resolve"
              ]
            }
          }
        }
      ]
    },
    {
      "name": "Leaderboard",
      "item": [
        {
          "name": "Top Players",
          "request": {
            "auth": {
              "type": "basic",
              "basic": [
                {
                  "key": "username",
                  "value": "{{username}}",
                  "type": "string"
                },
                {
                  "key": "password",
                  "value": "{{password}}",
                  "type": "string"
                }
              ]
            },
            "method": "GET",
            "header": [],
            "url": {
              "raw": "{{baseUrl}}/api/leaderboard/top",
              "host": [
                "{{baseUrl}}"
              ],
              "path": [
                "api",
                "leaderboard",
                "top"
              ]
            }
          }
        }
      ]
    }
  ],
  "variable": [
    {
      "key": "baseUrl",
      "value": "http://localhost:8081"
    },
    {
      "key": "username",
      "value": "allan"
    },
    {
      "key": "password",
      "value": "7895"
    },
    {
      "key": "adminUsername",
      "value": "admin"
    },
    {
      "key": "adminPassword",
      "value": "admin123"
    }
  ]
}